calculator_app/__init__.py
calculator_app/calculator_app.py
simple_streamlit_calculator-1.0.0.dist-info/METADATA
simple_streamlit_calculator-1.0.0.dist-info/WHEEL
simple_streamlit_calculator-1.0.0.dist-info/entry_points.txt
simple_streamlit_calculator-1.0.0.dist-info/top_level.txt
simple_streamlit_calculator-1.0.0.dist-info/RECORD
